{"cameraMode":{"drawMode":0,"name":"Shaded","section":"Shading Mode"},"sceneLighting":false,"audioPlay":false,"sceneViewState":{"showFog":true,"showMaterialUpdate":false,"showSkybox":false,"showFlares":true,"showImageEffects":true,"showParticleSystems":true},"in2DMode":false,"pivot":{"x":-5.193973064422607,"y":-4.181468486785889,"z":-2.3378262519836427},"rotation":{"x":0.24734477698802949,"y":-0.24944674968719483,"z":0.06606373190879822,"w":0.9339349269866943},"size":1.740696668624878,"orthographic":false}